neurogenesis/__init__.py
neurogenesis/models/__init__.py
neurogenesis/models/decision_tree.py
neurogenesis/models/knn.py
neurogenesis/models/linear_regression.py
neurogenesis/models/logistic_regression.py
neurogenesis/models/naive_bayes.py
neurogenesis/models/random_forest.py
neurogenesis/models/svm.py
neurogenesis-0.0.1.dist-info/METADATA
neurogenesis-0.0.1.dist-info/WHEEL
neurogenesis-0.0.1.dist-info/licenses/LICENSE
neurogenesis-0.0.1.dist-info/RECORD
