Metadata-Version: 2.4
Name: neurogenesis
Version: 0.0.1
Summary: A simple machine learning library for educational and experimantal purposes.
Project-URL: Homepage, https://github.com/ZainKhalidOfficial/neurogenesis
Project-URL: Issues, https://github.com/ZainKhalidOfficial/neurogenesis
Author-email: Zain Khalid <thezainkhalidofficial@gmail.com>
License-File: LICENSE
Classifier: License :: OSI Approved :: GNU General Public License v3 (GPLv3)
Classifier: Operating System :: OS Independent
Classifier: Programming Language :: Python :: 3
Requires-Python: >=3.0
